swcr/__init__.py
swcr/swcr.py
swcr/template.docx
swcr-1.0.1.dist-info/LICENSE.txt
swcr-1.0.1.dist-info/METADATA
swcr-1.0.1.dist-info/WHEEL
swcr-1.0.1.dist-info/entry_points.txt
swcr-1.0.1.dist-info/top_level.txt
swcr-1.0.1.dist-info/RECORD
