Metadata-Version: 2.1
Name: swcr
Version: 1.0.1
Summary: 计算机软件著作权程序鉴别材料（即源代码）生成器
Home-page: https://github.com/kenley2021/swcr
Author: kenley
Author-email: kenley2021@gmail.com
License: MIT
Platform: UNKNOWN
Classifier: License :: OSI Approved :: MIT License
Classifier: Programming Language :: Python
Classifier: Programming Language :: Python :: 3
Classifier: Programming Language :: Python :: 3.6
Classifier: Programming Language :: Python :: Implementation :: CPython
Classifier: Programming Language :: Python :: Implementation :: PyPy
Requires-Python: >=3.6.0
Requires-Dist: click
Requires-Dist: scandir
Requires-Dist: python-docx
